google/cloud/bigquery_biglake/__init__.py
google/cloud/bigquery_biglake/gapic_version.py
google/cloud/bigquery_biglake/py.typed
google/cloud/bigquery_biglake_v1/__init__.py
google/cloud/bigquery_biglake_v1/gapic_metadata.json
google/cloud/bigquery_biglake_v1/gapic_version.py
google/cloud/bigquery_biglake_v1/py.typed
google/cloud/bigquery_biglake_v1/services/__init__.py
google/cloud/bigquery_biglake_v1/services/metastore_service/__init__.py
google/cloud/bigquery_biglake_v1/services/metastore_service/async_client.py
google/cloud/bigquery_biglake_v1/services/metastore_service/client.py
google/cloud/bigquery_biglake_v1/services/metastore_service/pagers.py
google/cloud/bigquery_biglake_v1/services/metastore_service/transports/__init__.py
google/cloud/bigquery_biglake_v1/services/metastore_service/transports/base.py
google/cloud/bigquery_biglake_v1/services/metastore_service/transports/grpc.py
google/cloud/bigquery_biglake_v1/services/metastore_service/transports/grpc_asyncio.py
google/cloud/bigquery_biglake_v1/services/metastore_service/transports/rest.py
google/cloud/bigquery_biglake_v1/services/metastore_service/transports/rest_base.py
google/cloud/bigquery_biglake_v1/types/__init__.py
google/cloud/bigquery_biglake_v1/types/metastore.py
google/cloud/bigquery_biglake_v1alpha1/__init__.py
google/cloud/bigquery_biglake_v1alpha1/gapic_metadata.json
google/cloud/bigquery_biglake_v1alpha1/gapic_version.py
google/cloud/bigquery_biglake_v1alpha1/py.typed
google/cloud/bigquery_biglake_v1alpha1/services/__init__.py
google/cloud/bigquery_biglake_v1alpha1/services/metastore_service/__init__.py
google/cloud/bigquery_biglake_v1alpha1/services/metastore_service/async_client.py
google/cloud/bigquery_biglake_v1alpha1/services/metastore_service/client.py
google/cloud/bigquery_biglake_v1alpha1/services/metastore_service/pagers.py
google/cloud/bigquery_biglake_v1alpha1/services/metastore_service/transports/__init__.py
google_cloud_bigquery_biglake-0.6.0.dist-info/licenses/LICENSE
google_cloud_bigquery_biglake-0.6.0.dist-info/METADATA
google_cloud_bigquery_biglake-0.6.0.dist-info/WHEEL
google_cloud_bigquery_biglake-0.6.0.dist-info/top_level.txt
google_cloud_bigquery_biglake-0.6.0.dist-info/RECORD
